sqlog.py
sqlog-2.0.dist-info/LICENSE
sqlog-2.0.dist-info/METADATA
sqlog-2.0.dist-info/WHEEL
sqlog-2.0.dist-info/entry_points.txt
sqlog-2.0.dist-info/top_level.txt
sqlog-2.0.dist-info/RECORD
