Metadata-Version: 2.1
Name: sqlog
Version: 2.0
Summary: Hierarchical logging
Home-page: https://github.com/andriystr/sqlog
Author: Andriy Stremeluk
Author-email: astremeluk@gmail.com
License: MIT
Classifier: Programming Language :: Python :: 3.7
Classifier: License :: OSI Approved :: MIT License
Classifier: Operating System :: OS Independent
Requires-Python: >=3.7
License-File: LICENSE
